qde/__init__.py
qde/qde.py
qde/cli/__main__.py
qde/core/base.py
qde/core/registry.py
qde/metrics/scorers.py
qde/strategies/__init__.py
qde/strategies/base_strategy.py
qde/strategies/ces.py
qde/strategies/oes.py
qde-1.0.2.dist-info/licenses/LICENSE
qde-1.0.2.dist-info/METADATA
qde-1.0.2.dist-info/WHEEL
qde-1.0.2.dist-info/entry_points.txt
qde-1.0.2.dist-info/top_level.txt
qde-1.0.2.dist-info/RECORD
