Metadata-Version: 2.4
Name: qde
Version: 1.0.2
Summary: Quality Data Extractor (QDE): CES & OES filtering for synthetic data
Author: Pragati Sachdeva
License: MIT License
Project-URL: Homepage, https://github.com/pragatischdv/quality-data-extractor
Project-URL: Repository, https://github.com/pragatischdv/quality-data-extractor
Project-URL: Paper, https://doi.org/10.1109/ACCESS.2025.3603435
Keywords: synthetic data,data augmentation,filtering,feature selection,GANs
Classifier: Development Status :: 3 - Alpha
Classifier: Intended Audience :: Science/Research
Classifier: License :: OSI Approved :: MIT License
Classifier: Programming Language :: Python
Classifier: Programming Language :: Python :: 3
Classifier: Programming Language :: Python :: 3 :: Only
Classifier: Programming Language :: Python :: 3.9
Classifier: Programming Language :: Python :: 3.10
Classifier: Programming Language :: Python :: 3.11
Classifier: Programming Language :: Python :: 3.12
Classifier: Topic :: Scientific/Engineering :: Artificial Intelligence
Requires-Python: >=3.9
License-File: LICENSE
Requires-Dist: numpy>=1.22
Requires-Dist: pandas>=1.5
Requires-Dist: scikit-learn>=1.1
Requires-Dist: typer>=0.9
Requires-Dist: rich>=13.0
Dynamic: license-file
